README.md
setup.py
stylelens_index/__init__.py
stylelens_index/database_image.py
stylelens_index/database_object.py
stylelens_index/index_images.py
stylelens_index/index_objects.py
stylelens_index.egg-info/PKG-INFO
stylelens_index.egg-info/SOURCES.txt
stylelens_index.egg-info/dependency_links.txt
stylelens_index.egg-info/requires.txt
stylelens_index.egg-info/top_level.txt