Metadata-Version: 1.0
Name: stylelens-index
Version: 1.0.19
Summary: stylelens-index
Home-page: UNKNOWN
Author: UNKNOWN
Author-email: master@bluehack.net
License: UNKNOWN
Keywords: BlueLens,stylelens-index
Platform: UNKNOWN
